openphoton/__init__.py
openphoton/aperture_functions.py
openphoton/devices.py
openphoton/lenses.py
openphoton/rayleigh_sommerfeld.py
openphoton-0.1.7.dist-info/LICENSE
openphoton-0.1.7.dist-info/METADATA
openphoton-0.1.7.dist-info/WHEEL
openphoton-0.1.7.dist-info/top_level.txt
openphoton-0.1.7.dist-info/RECORD
